[
    {
        "name":"java.lang.String",
        "allPublicMethods":true
    },
    {
        "name":"java.nio.file.Files",
        "allPublicMethods":true
    },
    {
        "name":"java.io.File",
        "allPublicMethods":true
    },
    {
        "name":"java.lang.Byte",
        "allPublicConstructors":true,
        "allPublicMethods":true
    },
    {
        "name":"byte[]",
        "allDeclaredMethods":true,
        "allPublicMethods":true
    },
    {
        "name":"java.lang.Thread",
        "methods":[{"name":"<init>","parameterTypes":["java.lang.ThreadGroup","java.lang.Runnable","java.lang.String","long","boolean"] }]
    },
    {
        "name":"java.lang.reflect.Method",
        "methods":[
            {"name":"canAccess","parameterTypes":["java.lang.Object"] },
            {"name":"isDefault","parameterTypes":[] }
        ]
    },
    {
        "name": "java.lang.reflect.AccessibleObject",
        "methods" : [{"name":"canAccess"}]
    },
    {
        "name": "java.util.regex.Matcher",
        "allPublicMethods":true
    },
    {
      "name": "org.eclipse.collections.impl.map.mutable.primitive.IntShortHashMap",
      "allPublicMethods":true
    },
    {
      "name": "org.eclipse.collections.impl.map.mutable.primitive.IntObjectHashMap",
      "allPublicMethods":true
    },
    {
      "name": "org.eclipse.collections.impl.map.mutable.primitive.IntDoubleHashMap",
      "allPublicMethods":true
    },
    {
      "name": "org.eclipse.collections.impl.list.mutable.FastList",
      "allPublicMethods":true
    },
    {
      "name": "org.eclipse.collections.impl.map.mutable.UnifiedMap",
      "allPublicMethods":true
    },
    {
      "name": "org.eclipse.collections.impl.set.mutable.primitive.IntHashSet",
      "allPublicMethods":true
    },
    {
      "name": "org.eclipse.collections.api.set.primitive.MutableIntSet",
      "allPublicMethods":true
    },
    {
        "name": "java.text.Normalizer",
        "allPublicConstructors" : true,
        "allPublicMethods" : true,
        "allPublicFields" : true,
        "allPublicClasses" : true
    },
    {
        "name": "java.text.Normalizer$Form",
        "allPublicConstructors" : true,
        "allPublicMethods" : true,
        "allPublicFields" : true,
        "allPublicClasses" : true
    },
    {
        "name":"java.util.Date",
        "allPublicConstructors" : true,
        "allPublicMethods" : true,
        "allPublicFields" : true,
        "allPublicClasses" : true
    },
    {
        "name":"java.util.concurrent.ConcurrentLinkedQueue",
        "methods":[
            {"name":"iterator","parameterTypes":[] }
        ]
    },
    {
        "name":"sun.security.provider.NativePRNG",
        "methods":[{"name":"<init>","parameterTypes":[] }]
    },
    {
      "name":"datalevin.binding.graal.LMDB",
      "allDeclaredConstructors" : true,
      "allPublicConstructors" : true,
      "allDeclaredMethods" : true,
      "allPublicMethods" : true,
      "allDeclaredClasses" : true,
      "allPublicFields" : true,
      "allDeclaredFields" : true,
      "allPublicClasses" : true
    },
    {
        "name":"datalevin.binding.graal.DBI",
        "allDeclaredConstructors" : true,
        "allPublicConstructors" : true,
        "allDeclaredMethods" : true,
        "allPublicMethods" : true,
        "allDeclaredClasses" : true,
        "allPublicFields" : true,
        "allDeclaredFields" : true,
        "allPublicClasses" : true
    },
    {
        "name":"datalevin.entity.Entity",
        "allDeclaredConstructors" : true,
        "allPublicConstructors" : true,
        "allDeclaredMethods" : true,
        "allPublicMethods" : true,
        "allDeclaredClasses" : true,
        "allPublicFields" : true,
        "allDeclaredFields" : true,
        "allPublicClasses" : true
    },
    {
        "name":"datalevin.bits.Retrieved",
        "allDeclaredConstructors" : true,
        "allPublicConstructors" : true,
        "allDeclaredMethods" : true,
        "allPublicMethods" : true,
        "allDeclaredClasses" : true,
        "allPublicFields" : true,
        "allDeclaredFields" : true,
        "allPublicClasses" : true
    },
    {
        "name":"sun.security.provider.SHA",
        "methods":[{"name":"<init>","parameterTypes":[] }]
    },
    {
        "name":"net.jpountz.lz4.LZ4JavaSafeCompressor",
        "allDeclaredConstructors" : true,
        "allPublicConstructors" : true,
        "allDeclaredMethods" : true,
        "allPublicMethods" : true,
        "allDeclaredClasses" : true,
        "allPublicFields" : true,
        "allDeclaredFields" : true,
        "allPublicClasses" : true
    },
    {
        "name":"net.jpountz.lz4.LZ4JavaSafeSafeDecompressor",
        "allDeclaredConstructors" : true,
        "allPublicConstructors" : true,
        "allDeclaredMethods" : true,
        "allPublicMethods" : true,
        "allDeclaredClasses" : true,
        "allPublicFields" : true,
        "allDeclaredFields" : true,
        "allPublicClasses" : true
    },
    {
        "name":"net.jpountz.lz4.LZ4JavaSafeFastDecompressor",
        "allDeclaredConstructors" : true,
        "allPublicConstructors" : true,
        "allDeclaredMethods" : true,
        "allPublicMethods" : true,
        "allDeclaredClasses" : true,
        "allPublicFields" : true,
        "allDeclaredFields" : true,
        "allPublicClasses" : true
    },
    {
        "name":"net.jpountz.lz4.LZ4HCJavaSafeCompressor",
        "allDeclaredConstructors" : true,
        "allPublicConstructors" : true,
        "allDeclaredMethods" : true,
        "allPublicMethods" : true,
        "allDeclaredClasses" : true,
        "allPublicFields" : true,
        "allDeclaredFields" : true,
        "allPublicClasses" : true
    },
    {
        "name":"[Ljava.util.Date;",
        "allPublicConstructors" : true,
        "allPublicMethods" : true,
        "allPublicFields" : true,
        "allPublicClasses" : true
    },
    {
        "name":"[Ldatalevin.search.Candidate;",
        "allPublicConstructors" : true,
        "allPublicMethods" : true,
        "allPublicFields" : true,
        "allPublicClasses" : true
    }
]
